verve/__init__.py
verve/queries.py
verve/data_generation/__init__.py
verve/data_generation/dataGen.py
verve/data_generation/dataset_labelmatcher.py
verve/data_generation/grammartree.py
verve/dev_pipeliner/__init__.py
verve/dev_pipeliner/pipeline_sample.py
verve/dev_pipeliner/regression_split_functions.py
verve/modeling/__init__.py
verve/modeling/prediction_model_creation.py
verve/modeling/tuner.py
verve/plotting/__init__.py
verve/plotting/generate_plots.py
verve/plotting/nonkeras_generate_plots.py
verve/preprocessing/NLP_preprocessing.py
verve/preprocessing/__init__.py
verve/preprocessing/data_preprocesser.py
verve/preprocessing/data_reader.py
verve/preprocessing/huggingface_model_finetune_helper.py
verve/preprocessing/image_caption_helpers.py
verve/preprocessing/image_preprocesser.py
verve/query/__init__.py
verve/query/classification_models.py
verve/query/dimensionality_red_queries.py
verve/query/feedforward_nn.py
verve/query/nlp_queries.py
verve/query/supplementaries.py
verve/query/unused_functions.py
verve-0.0.1.dist-info/LICENSE.txt
verve-0.0.1.dist-info/METADATA
verve-0.0.1.dist-info/WHEEL
verve-0.0.1.dist-info/top_level.txt
verve-0.0.1.dist-info/RECORD
