Metadata-Version: 2.1
Name: verve
Version: 0.0.1
Summary: Fully automated machine learning in one-liners.
Home-page: https://github.com/Palashio/verve
Author: Palash Shah
Author-email: ps9cmk@virginia.edu
License: UNKNOWN
Platform: UNKNOWN
Classifier: Programming Language :: Python :: 3
Classifier: License :: OSI Approved :: MIT License
Classifier: Operating System :: OS Independent
Requires-Python: >=3.6
